vmaudit/__init__.py
vmaudit/__main__.py
vmaudit/app.py
vmaudit/lib/__init__.py
vmaudit/lib/cmdline.py
vmaudit/lib/color.py
vmaudit/lib/vma.py
vmaudit-1.0.1.dist-info/METADATA
vmaudit-1.0.1.dist-info/WHEEL
vmaudit-1.0.1.dist-info/entry_points.txt
vmaudit-1.0.1.dist-info/licenses/LICENSE
vmaudit-1.0.1.dist-info/RECORD
