Metadata-Version: 2.4
Name: vmaudit
Version: 1.0.1
Summary: Analyzes Virtual Memory Area (VMA) utilization to provide data-driven recommendations for system administrators and developers.
Project-URL: Homepage, https://github.com/Arcitec/vmaudit
Project-URL: Repository, https://github.com/Arcitec/vmaudit.git
Author: Arcitec
License-Expression: GPL-2.0-only
License-File: LICENSE
Keywords: analysis,audit,kernel,linux,linux tools,memory,memory usage,monitoring,performance,sysadmin,system administration,virtual memory,vm.max_map_count,vma,vmstat
Classifier: Development Status :: 5 - Production/Stable
Classifier: Environment :: Console
Classifier: Intended Audience :: Developers
Classifier: Intended Audience :: System Administrators
Classifier: Natural Language :: English
Classifier: Operating System :: POSIX :: Linux
Classifier: Programming Language :: Python :: 3
Classifier: Programming Language :: Python :: 3.9
Classifier: Programming Language :: Python :: 3.10
Classifier: Programming Language :: Python :: 3.11
Classifier: Programming Language :: Python :: 3.12
Classifier: Programming Language :: Python :: 3.13
Classifier: Programming Language :: Python :: 3.14
Classifier: Programming Language :: Python :: 3.15
Classifier: Topic :: Software Development :: Quality Assurance
Classifier: Topic :: Software Development :: Testing
Classifier: Topic :: System :: Monitoring
Classifier: Topic :: System :: Operating System Kernels :: Linux
Classifier: Topic :: System :: Systems Administration
Classifier: Topic :: Utilities
Requires-Python: >=3.9
